MANIFEST.in
README.txt
setup.cfg
setup.py
docs/HISTORY.txt
docs/INSTALL.txt
docs/LICENSE.GPL
docs/LICENSE.txt
quintagroup/__init__.py
quintagroup.analytics.egg-info/PKG-INFO
quintagroup.analytics.egg-info/SOURCES.txt
quintagroup.analytics.egg-info/dependency_links.txt
quintagroup.analytics.egg-info/entry_points.txt
quintagroup.analytics.egg-info/namespace_packages.txt
quintagroup.analytics.egg-info/not-zip-safe
quintagroup.analytics.egg-info/requires.txt
quintagroup.analytics.egg-info/top_level.txt
quintagroup/analytics/README.txt
quintagroup/analytics/__init__.py
quintagroup/analytics/config.py
quintagroup/analytics/configure.zcml
quintagroup/analytics/tests.py
quintagroup/analytics/browser/__init__.py
quintagroup/analytics/browser/configure.zcml
quintagroup/analytics/browser/legacy_portlets.pt
quintagroup/analytics/browser/ownership_by_state.pt
quintagroup/analytics/browser/ownership_by_type.pt
quintagroup/analytics/browser/portlets_stats.pt
quintagroup/analytics/browser/properties_stats.pt
quintagroup/analytics/browser/qa_overview.pt
quintagroup/analytics/browser/type_by_state.pt
quintagroup/analytics/browser/views.py
quintagroup/analytics/browser/resources/qaicon.png
quintagroup/analytics/browser/resources/stats_style.css
quintagroup/analytics/locales/quintagroup.analytics.pot
quintagroup/analytics/locales/fr/LC_MESSAGES/quintagroup.analytics.po
quintagroup/analytics/profiles/default/controlpanel.xml