Metadata-Version: 1.0
Name: quintagroup.analytics
Version: 1.1
Summary: Plone site's statistics
Home-page: http://svn.quintagroup.com/products/quintagroup.analytics
Author: Quintagroup
Author-email: support@quintagroup.com
License: GPL
Platform: UNKNOWN
Classifier: Framework :: Plone
Classifier: Programming Language :: Python
Classifier: Topic :: Software Development :: Libraries :: Python Modules
